antonio_pkg/__init__.py
antonio_pkg/antonio_pkg.py
antonio_pkg-0.1.2.dist-info/METADATA
antonio_pkg-0.1.2.dist-info/WHEEL
antonio_pkg-0.1.2.dist-info/top_level.txt
antonio_pkg-0.1.2.dist-info/RECORD
